ipdm-0.1.4.dist-info/METADATA
ipdm-0.1.4.dist-info/WHEEL
ipdm-0.1.4.dist-info/entry_points.txt
ipm/__init__.py
ipm/__main__.py
ipm/api.py
ipm/const.py
ipm/exceptions.py
ipm/logging.py
ipm/models/__init__.py
ipm/models/index.py
ipm/models/ipk.py
ipm/models/lock.py
ipm/typing.py
ipm/utils/__init__.py
ipm/utils/_freeze.py
ipm/utils/freeze.py
ipm/utils/hash.py
ipm/utils/loader.py
ipm/utils/urlparser.py
ipm/utils/uuid.py
ipm/utils/version.py
ipdm-0.1.4.dist-info/RECORD
